{
  "ItemType": 25,
  "Id": 12161,
  "Body": {
    "Type": 2,
    "Size": 1.0,
    "Lifetime": 1.0,
    "BulletPrefab": 14009
  },
  "Triggers": [
    {
      "Condition": 1,
      "EffectType": 1,
      "VisualEffect": 14014,
      "AudioClip": "launch_02",
      "Size": 1.0,
      "Lifetime": 1.2
    },
    {
      "Condition": 1,
      "EffectType": 1,
      "VisualEffect": 1,
      "Size": 2.0,
      "Lifetime": 0.2
    },
    {
      "Condition": 5,
      "EffectType": 1,
      "VisualEffect": 1,
      "Size": 2.5,
      "Lifetime": 0.2
    },
    {
      "Condition": 1,
      "EffectType": 1,
      "VisualEffect": 1,
      "Color": "#00FFFFFF",
      "ColorMode": 2,
      "Size": 1.0,
      "Lifetime": 1.2
    }
  ],
  "ImpactType": 2,
  "Effects": [
    {
      "Type": 5,
      "DamageType": 1,
      "Power": 1.0
    }
  ]
}